file_process/__init__.py
file_process/base.py
file_process/constants.py
file_process/exceptions.py
file_process/file_processor_factory.py
file_process/logger.py
file_process/csv/__init__.py
file_process/csv/csv_processor.py
file_process/csv/csv_validator.py
file_process/csv/schemas.py
file_process/h5ad/__init__.py
file_process/h5ad/h5ad_processor.py
file_process/h5ad/h5ad_validator.py
file_process/h5ad/schemas.py
file_process/txt/__init__.py
file_process/txt/txt_processor.py
file_process-1.4.6.dist-info/LICENSE.txt
file_process-1.4.6.dist-info/METADATA
file_process-1.4.6.dist-info/WHEEL
file_process-1.4.6.dist-info/top_level.txt
file_process-1.4.6.dist-info/RECORD
