Metadata-Version: 2.2
Name: file_process
Version: 1.4.6
Summary: A package that does file validation and file preview.
Home-page: https://github.com/Superbio-ai/file-process
Author: superbio.ai
License: MIT
License-File: LICENSE.txt
Requires-Dist: pandas==2.2
Requires-Dist: anndata==0.10.5
Requires-Dist: numpy>=1.21
Dynamic: author
Dynamic: description
Dynamic: description-content-type
Dynamic: home-page
Dynamic: license
Dynamic: requires-dist
Dynamic: summary
